Makefile
README.txt
setup.cfg
setup.py
docs/Makefile
docs/make.bat
docs/source/HISTORY.rst
docs/source/conf.py
docs/source/content-types.rst
docs/source/index.rst
docs/source/installation.rst
docs/source/integration-ploneformgen.rst
docs/source/resource-directories.rst
zopyx/__init__.py
zopyx.smartprintng.plone.egg-info/PKG-INFO
zopyx.smartprintng.plone.egg-info/SOURCES.txt
zopyx.smartprintng.plone.egg-info/dependency_links.txt
zopyx.smartprintng.plone.egg-info/entry_points.txt
zopyx.smartprintng.plone.egg-info/namespace_packages.txt
zopyx.smartprintng.plone.egg-info/not-zip-safe
zopyx.smartprintng.plone.egg-info/requires.txt
zopyx.smartprintng.plone.egg-info/top_level.txt
zopyx/smartprintng/__init__.py
zopyx/smartprintng/plone/__init__.py
zopyx/smartprintng/plone/configure.zcml
zopyx/smartprintng/plone/header.txt
zopyx/smartprintng/plone/interfaces.py
zopyx/smartprintng/plone/logger.py
zopyx/smartprintng/plone/meta.zcml
zopyx/smartprintng/plone/resources.py
zopyx/smartprintng/plone/zcml.py
zopyx/smartprintng/plone/browser/__init__.py
zopyx/smartprintng/plone/browser/compatible.py
zopyx/smartprintng/plone/browser/configure.zcml
zopyx/smartprintng/plone/browser/images.py
zopyx/smartprintng/plone/browser/pdf.py
zopyx/smartprintng/plone/browser/preflight.pt
zopyx/smartprintng/plone/browser/sorting.py
zopyx/smartprintng/plone/browser/splitter.py
zopyx/smartprintng/plone/browser/util.py
zopyx/smartprintng/plone/browser/tests/__init__.py
zopyx/smartprintng/plone/browser/types/__init__.py
zopyx/smartprintng/plone/browser/types/dexterity.pt
zopyx/smartprintng/plone/browser/types/dexterity.py
zopyx/smartprintng/plone/browser/types/document.pt
zopyx/smartprintng/plone/browser/types/document.py
zopyx/smartprintng/plone/browser/types/folder.py
zopyx/smartprintng/plone/browser/types/folder_flat.py
zopyx/smartprintng/plone/browser/types/folder_nested.py
zopyx/smartprintng/plone/browser/types/glossary.pt
zopyx/smartprintng/plone/browser/types/glossary.py
zopyx/smartprintng/plone/browser/types/newsitem.pt
zopyx/smartprintng/plone/browser/types/newsitem.py
zopyx/smartprintng/plone/browser/types/pfg.py
zopyx/smartprintng/plone/browser/types/topic.py
zopyx/smartprintng/plone/extender/__init__.py
zopyx/smartprintng/plone/extender/document.py
zopyx/smartprintng/plone/extender/image.py
zopyx/smartprintng/plone/resources_default/ArialUnicode.ttf
