Metadata-Version: 1.0
Name: zopyx.smartprintng.plone
Version: 2.1.26
Summary: Produce & Publisher server integration with Plone
Home-page: http://pypi.python.org/pypi/zopyx.smartprintng.plone
Author: Andreas Jung
Author-email: info@zopyx.com
License: GPL
Keywords: PDF Plone Python EBook EPUB
Platform: UNKNOWN
Classifier: Programming Language :: Python
Classifier: Framework :: Plone
Classifier: Framework :: Plone :: 4.0
Classifier: Framework :: Plone :: 4.1
Classifier: Framework :: Plone :: 4.2
Classifier: Framework :: Zope2
Classifier: Topic :: Software Development :: Libraries :: Python Modules
